Metadata-Version: 1.0
Name: sqlite-checkforeignkeys
Version: 1.0.3
Summary: A sqlite engine that checks foreign keys
Home-page: https://github.com/hulu/sqlite_checkforeignkeys
Author: McKay Salisbury
Author-email: mckay.salisbury@hulu.com
License: UNKNOWN
Keywords: foreign key,sqlite
Platform: UNKNOWN
